lean4_jupyter/__init__.py
lean4_jupyter/__main__.py
lean4_jupyter/display.py
lean4_jupyter/install.py
lean4_jupyter/kernel.py
lean4_jupyter/repl.py
lean4_jupyter/resources/__init__.py
lean4_jupyter/resources/lean_logo.svg
lean4_jupyter-0.0.2.dist-info/LICENSE
lean4_jupyter-0.0.2.dist-info/WHEEL
lean4_jupyter-0.0.2.dist-info/METADATA
lean4_jupyter-0.0.2.dist-info/RECORD
