Metadata-Version: 2.3
Name: lean4_jupyter
Version: 0.0.2
Summary: lean4_jupyter: A Lean 4 Jupyter kernel via REPL
Author-email: Utensil Song <utensilcandel@gmail.com>
Classifier: Framework :: Jupyter
Classifier: License :: OSI Approved :: MIT License
Classifier: Programming Language :: Python :: 3
Classifier: Operating System :: MacOS
Classifier: Operating System :: POSIX :: Linux
Classifier: Development Status :: 3 - Alpha
Requires-Dist: pexpect (>=4.0)
Requires-Dist: ipykernel
Requires-Dist: alectryon
Requires-Dist: flake8 ; extra == "test"
Requires-Dist: pytest ; extra == "test"
Requires-Dist: nbval ; extra == "test"
Requires-Dist: papermill ; extra == "test"
Project-URL: Source, https://github.com/utensil/lean4_jupyter
Provides-Extra: test
